[
  {
    "id": "123ab",
    "productHeader": "Iphone 11 64GB",
    "sellerID": "44",
    "price": 700,
    "productComments": []
  },
  {
    "id": "wowo",
    "productHeader": "foo",
    "sellerID": "44",
    "price": 15,
    "productComments": []
  },
  {
    "id": "car12",
    "productHeader": "a new bmw",
    "sellerID": "44",
    "price": 20000,
    "productComments": []
  },
  {
    "id": "thirdItemId123",
    "productHeader": "gray coffe cup",
    "sellerID": "44",
    "price": 10,
    "productComments": []
  },
  {
    "id": "dummyItemId55",
    "productHeader": "(dummy item productHeader)",
    "sellerID": "55",
    "price": 10,
    "productComments": []
  },
  {
    "id": "abc12",
    "productHeader": "axiosCreated Item",
    "sellerID": "44",
    "price": 22,
    "productComments": []
  },
  {
    "id": "abc12",
    "productHeader": "axiosCreated Item",
    "sellerID": "44",
    "price": 22,
    "productComments": []
  },
  {
    "id": "abc12",
    "productHeader": "axiosCreated Item",
    "sellerID": "44",
    "price": 22,
    "productComments": []
  },
  {
    "id": "abc12",
    "productHeader": "axiosCreated Item",
    "sellerID": "44",
    "price": 22,
    "productComments": []
  }
]